cli_completer/__init__.py
cli_completer/complete.py
cli_completer/rl_completer.py
cli_completer/core/__init__.py
cli_completer/core/abc.py
cli_completer/core/callback.py
cli_completer/core/exception.py
cli_completer-0.0.1.dist-info/METADATA
cli_completer-0.0.1.dist-info/WHEEL
cli_completer-0.0.1.dist-info/licenses/LICENSE
cli_completer-0.0.1.dist-info/RECORD
