Metadata-Version: 2.3
Name: cli_completer
Version: 0.0.1
Summary: Completer for CLI
Author-email: Chuangtao Chen <cocytus@outlook.com>
License: MIT License
License-File: LICENSE
Keywords: cli,completer,utility
Classifier: Development Status :: 3 - Alpha
Classifier: License :: OSI Approved :: MIT License
Classifier: Operating System :: OS Independent
Classifier: Programming Language :: Python :: 3
Requires-Python: >=3.8
Requires-Dist: pyreadline3; os_name == 'nt'
